{ 
	"tenantId": "mp",
    	"moduleName": "common-masters",
    	"Department": [{
            "name": "DIRECTORATE PUBLIC INSTRUCTION",
            "code": "DP001",
            "active": true
        },
        {
            "name": "RAJYA SIKSHA KENDRA",
            "code": "DP002",
            "active": true
        },
	    {
            "name": "BOARD OF SEC EDUCATION",
            "code": "DP003",
            "active": true
        },
	    {
            "name": "OPEN SCHOOL SCHOOL",
            "code": "DP004",
            "active": true
        },
	    {
            "name": "MADARASA BOARD",
            "code": "DP005",
            "active": true
        },
	    {
            "name": "TEXT BOOK CORP.",
            "code": "DP006",
            "active": true
        },
	    {
            "name": "SCOUT AND GUIDE",
            "code": "DP007",
            "active": true
        },
	    {
            "name": "NCC NATIONAL CADET CORE",
            "code": "DP008",
            "active": true
        }

    ]
}